jh_finance_api/__init__.py
jh_finance_api/financial_list.ipynb
jh_finance_api/financial_list.py
jh_finance_api/financial_ratios.ipynb
jh_finance_api/financial_ratios.py
jh_finance_api/financial_raw.ipynb
jh_finance_api/financial_raw.py
jh_finance_api/index_us_dowjones.ipynb
jh_finance_api/index_us_dowjones.py
jh_finance_api/index_us_nasdaq100.ipynb
jh_finance_api/index_us_nasdaq100.py
jh_finance_api/index_us_sp500.ipynb
jh_finance_api/index_us_sp500.py
jh_finance_api/info.ipynb
jh_finance_api/info.py
jh_finance_api/market_history.ipynb
jh_finance_api/market_history.py
jh_finance_api/options_stack.ipynb
jh_finance_api/options_stack.py
jh_finance_api/options_stack_2.ipynb
jh_finance_api/options_stack_2.py
jh_finance_api-0.1.21.dist-info/METADATA
jh_finance_api-0.1.21.dist-info/WHEEL
jh_finance_api-0.1.21.dist-info/RECORD
